{
    "id": "visuflow",
    "title": "VisuFlow",
    "description": "Lateral Flow detection pipeline",
    "categories": [
        "lfa"
    ],
    "inputs": [
        {
            "id": "input_dir",
            "title": "LFA Images",
            "input_type": "file",
            "description": "1 or more LFA images",
            "count": "multiple",
            "file_types": [
                "image/jpeg",
                "image/png"
            ],
            "optional": false
        }
    ],
    "pipeline_type": "containerized",
    "repository": "mshunjan/visuflow",
    "report_inputs": {
        "detection": "detection_result.csv"
    }
}